phonexia_emotion_recognition_client.py
phonexia_emotion_recognition_client-2.0.1.dist-info/METADATA
phonexia_emotion_recognition_client-2.0.1.dist-info/WHEEL
phonexia_emotion_recognition_client-2.0.1.dist-info/entry_points.txt
phonexia_emotion_recognition_client-2.0.1.dist-info/top_level.txt
phonexia_emotion_recognition_client-2.0.1.dist-info/RECORD
